{
  "SavePets": "Збережи улюбленців",
  "LANG": {
    "UA": "Українська",
    "EN": "Англійська"
  },
  "profile.personal.header": "Ваші особісті дані",
  "Users": "Користувачі",
  "Logout": "Вийти",
  "Register": "Зареєструватись",
  "Login": "Увійти",
  "Email": "Пошта",
  "Password": "Пароль",
  "Name": "Ім'я",
  "Dob": "Дата народження",
  "Title": "Назва",
  "Type": "Тип",
  "Save": "Зберегти",
  "AddNew": "Додати новий",
  "Id": "Id",
  "Actions": "Дії",
  "Delete": "Видалити",
  "Edit": "Оновити",
  "Value": "Значення",
  "Date": "Дата",
  "NewUser": "Створення нового користувача",
  "Role": "Роль",
  "User": "Користувач",
  "Admin": "Адміністратор",
  "EditUser": "Редагування користувача",
  "Profile": "Профіль",
  "UserList": "Список користувачів",
  "UserProfile": "Профіль користувача",
  "MyProfile": "Мій профіль",
  "Description": "Опис",
  "MeasurementList": "Список даних",
  "NewMeasurement": "Додавання нових даних",
  "Measurements": "Дані",
  "EditMeasurement": "Редагвання даних",
  "CreateDate": "Дата створення",
  "MeasurementsChart": "Графіки даних",
  "Update": "Оновити",
  "Position": "Позиція",
  "Enterprise": "Підприємство",
  "Status": "Статус",
  "Status from": "Статус з",
  "Start": "Початок",
  "Finish": "Закінчення",
  "End": "Закінчення",
  "Address": "Адреса",
  "MesurementsCharts": "Статистика",
  "CreateUser": "Створення користувача",
  "Devices": "Датчики",
  "DeviceList": "Список датчиків",
  "Kind": "Вид",
  "All": "Всі",
  "Own": "Власні",
  "Other": "Інші",
  "View": "Перегляд",
  "ViewDevice": "Перегляд датчика",
  "TakeAccess": "Надати доступ",
  "Device": "Датчик",
  "AirType": "Повітряний",
  "WaterType": "Водяний",
  "EditDevice": "Редагування датчика",
  "CreateDevice": "Створення датчика",
  "CreateMeasurement": "Створення даних",
  "Aquarium": "Акваріум",
  "AquariumList": "Список акваріумів",
  "Height": "Висота",
  "Width": "Ширина",
  "Length": "Довжина",
  "Volume": "Об'єм",
  "EditAquarium": "Редагування акваріуму",
  "CreateAquarium": "Сторення акваріума",
  "SchedulesList": "Розклади",
  "EditSchedule": "Редагування розкладу",
  "CreateSchedule": "Створення розкладу",
  "Aquariums": "Акваріуми",
  "Schedules": "Розклади",
  "On": "Включення",
  "Off": "Виключення",
  "Temperature": "Температура, *",
  "Pollution": "Забрудненість, %",
  "Greenhouses": "Теплиці",
  "GreenhouseList": "Список теплиць",
  "EditGreenhouse": "Редагування теплиці",
  "CreateGreenhouse": "Створення теплиці",
  "Greenhouse": "Теплиця",
  "Humidity": "Вологість, %",
  "WorkingDevice": "Датчик роботи",
  "MeasuringDevice": "Датчик вимірювання",
  "WarmedUp": "Нагрівання",
  "Moisturizer": "Зволоження",
  "WorkCycles": "Робочі цикли",
  "WorkCycleList": "Список робочих циклів",
  "RunValue": "Значення запуску",
  "StopValue": "Значення зупинки",
  "CreateWorkCycle": "Створення робочого циклу",
  "EditWorkCycle": "Редагування робочого циклу",
  "CreateSuccess": "Створення успішно",
  "UpdatedSuccess": "Редагування успішно",
  "IsBanned": "Заблокований",
  "Telegram": "Телеграм",
  "Instagram": "Інстаграм",
  "Phone": "Телефон",
  "Viber": "Вайбер",
  "Facebook": "Фейсбук",
  "Ban": "Заблокувати",
  "UnBan": "Розблокувати",
  "No": "Ні",
  "Yes": "Так",
  "AnimalList": "Список тварин",
  "Search": "Пошук",
  "Cat": "Кіт",
  "Dog": "Собака",
  "IsFounded": "В розшуку",
  "Animals": "Тварини",
  "AnimalView": "Перегляд тварини",
  "Latitude": "Широта",
  "Longitude": "Довгота",
  "EditAnimal": "Редагвання тварини",
  "UploadPhoto": "Завантаження фото",
  "CreateAnimal": "Створення тварини"
}
